intuit_oauth-1.2.6-py3.10-nspkg.pth
intuitlib/client.py
intuitlib/config.py
intuitlib/enums.py
intuitlib/exceptions.py
intuitlib/migration.py
intuitlib/utils.py
intuitlib/version.py
intuit_oauth-1.2.6.dist-info/LICENSE
intuit_oauth-1.2.6.dist-info/METADATA
intuit_oauth-1.2.6.dist-info/WHEEL
intuit_oauth-1.2.6.dist-info/namespace_packages.txt
intuit_oauth-1.2.6.dist-info/top_level.txt
intuit_oauth-1.2.6.dist-info/RECORD
