Metadata-Version: 2.1
Name: intuit-oauth
Version: 1.2.6
Summary: Intuit OAuth Client
Home-page: https://github.com/intuit/oauth-pythonclient
Author: Intuit Inc
Author-email: IDGSDK@intuit.com
License: Apache 2.0
Keywords: intuit quickbooks oauth auth openid client
License-File: LICENSE
Requires-Dist: pyjwt[crypto]>=2.0.0
Requires-Dist: requests>=2.13.0
Requires-Dist: requests_oauthlib>=1.0.0
Requires-Dist: six>=1.10.0
Requires-Dist: enum-compat
